{
  "reactivate": {
    "message": "Your 14-day trial was successfully reactivated. You can now utilize Nightwatch to improve your website visibility at its full power.",
    "buttonText": "Login to Nightwatch",
    "buttonLink": "https://app.nightwatch.io/login?ref=reactivation"
  },
  "nouser": {
    "message": "No user matching the criteria. You can still register and start using Nightwatch.",
    "buttonText": "Sign-up Now",
    "buttonLink": "https://app.nightwatch.io/signup?ref=nouser"
  },
  "nps": {
    "input": true,
    "inputType": "nps",
    "npsQuestion": "How likely are you to recommend Nightwatch to a friend or colleague?",
    "inputMessage": "What's the reason for your rating?",
    "inputButtonText": "Send Feedback",
    "inputSubmitUrl": "https://wopeauyedwfkdvultzqt.supabase.co/functions/v1/c/nightwatch-nps",
    "message": "Thank you for your feedback.",
    "buttonText": "Login to Nightwatch",
    "buttonLink": "https://app.nightwatch.io/login?ref=nps"
  }
}
